torch_liberator/__init__.py
torch_liberator/__main__.py
torch_liberator/cli.py
torch_liberator/deployer.py
torch_liberator/exporter.py
torch_liberator/initializer.py
torch_liberator/xpu_device.py
torch_liberator/util/__init__.py
torch_liberator/util/util_zip.py
torch_liberator-0.2.1.dist-info/LICENSE
torch_liberator-0.2.1.dist-info/METADATA
torch_liberator-0.2.1.dist-info/WHEEL
torch_liberator-0.2.1.dist-info/top_level.txt
torch_liberator-0.2.1.dist-info/RECORD
